Workbook

Sheet Charts
A3: Row Labels | B3: Sum of Sales | D3: Row Labels | E3: Sum of Sales | G3: Row Labels | H3: Sum of Sales
A4: Furniture | B4: 728658.58 | D4: Central | E4: 492646.91 | G4: Accessories | H4: 164186.7
A5: Office Supplies | B5: 705422.33 | D5: East | E5: 669518.73 | G5: Appliances | H5: 104618.4
A6: Technology | B6: 827455.87 | D6: South | E6: 389151.46 | G6: Art | H6: 26705.41
A7: Grand Total | B7: 2261536.8 | D7: West | E7: 710219.68 | G7: Binders | H7: 200028.79
D8: Grand Total | E8: 2261536.8 | G8: Bookcases | H8: 113813.2
G9: Chairs | H9: 322822.73
G10: Copiers | H10: 146248.09
G11: Envelopes | H11: 16128.046
G12: Fasteners | H12: 3001.96
G13: Furnishings | H13: 89212.018
G14: Labels | H14: 12347.726
G15: Machines | H15: 189238.63
G16: Paper | H16: 76828.304
G17: Phones | H17: 327782.45
G18: Storage | H18: 219343.39
G19: Supplies | H19: 46420.308
G20: Tables | H20: 202810.63
G21: Grand Total | H21: 2261536.8
A39: Sum of Sales | B39: Column Labels | G39: Row Labels | H39: Sum of Sales
A40: Row Labels | B40: Consumer | C40: Corporate | D40: Home Office | E40: Grand Total | G40: Sean Miller | H40: 25043.05
A41: Central | B41: 250210.52 | C41: 152031.5 | D41: 90404.894 | E41: 492646.91 | G41: Tamara Chand | H41: 19052.218
A42: East | B42: 347906.61 | C42: 195897.42 | D42: 125714.7 | E42: 669518.73 | G42: Raymond Buch | H42: 15117.339
A43: South | B43: 194702.21 | C43: 120546.87 | D43: 73902.372 | E43: 389151.46 | G43: Tom Ashbrook | H43: 14595.62
A44: West | B44: 355241.19 | C44: 220018.28 | D44: 134960.21 | E44: 710219.68 | G44: Adrian Barton | H44: 14473.571
A45: Grand Total | B45: 1148060.5 | C45: 688494.07 | D45: 424982.18 | E45: 2261536.8 | G45: Ken Lonsdale | H45: 14175.229
G46: Sanjit Chand | H46: 14142.334
A47: Row Labels | B47: Sum of Sales | G47: Hunter Lopez | H47: 12873.298
A48: 2015 | B48: 479856.21 | G48: Sanjit Engle | H48: 12209.438
A49: Jan | B49: 14205.707 | G49: Christopher Conant | H49: 12129.072
A50: Feb | B50: 4519.892 | G50: Grand Total | H50: 153811.17
A51: Mar | B51: 55205.797
A52: Apr | B52: 27906.855
A53: May | B53: 23644.303
A54: Jun | B54: 34322.936
A55: Jul | B55: 33781.543
A56: Aug | B56: 27117.536
A57: Sep | B57: 81623.527
A58: Oct | B58: 31453.393
A59: Nov | B59: 77907.661
A60: Dec | B60: 68167.058
A61: 2016 | B61: 459436.01
A62: Jan | B62: 18066.958
... A100: Grand Total | B100: 2261536.8

Sheet train
A1: Row ID | B1: Order ID | C1: Order Date | D1: Ship Date | E1: Ship Mode | F1: Customer ID | G1: Customer Name | H1: Segment | I1: Country | J1: City | K1: State | L1: Postal Code | M1: Region | N1: Product ID | O1: Category | P1: Sub-Category | Q1: Product Name | R1: Sales | S1: Sum | T1: Count | U1: If
A2: 1 | B2: CA-2017-152156 | C2: 43047 | D2: 43050 | E2: Second Class | F2: CG-12520 | G2: Claire Gute | H2: Consumer | I2: United States | J2: Henderson | K2: Kentucky | L2: 42420 | M2: South | N2: FUR-BO-10001798 | O2: Furniture | P2: Bookcases | Q2: Bush Somerset Collection Bookcase | R2: 261.96 | S2: =SUM(R2:R9801) -> 2261536.8 | T2: =COUNT(R2:R9801) -> 9800 | U2: =IF(R2>=500,"High","Low") -> Low
A3: 2 | B3: CA-2017-152156 | C3: 43047 | D3: 43050 | E3: Second Class | F3: CG-12520 | G3: Claire Gute | H3: Consumer | I3: United States | J3: Henderson | K3: Kentucky | L3: 42420 | M3: South | N3: FUR-CH-10000454 | O3: Furniture | P3: Chairs | Q3: Hon Deluxe Fabric Upholstered Stacking Chairs, Rounded Back | R3: 731.94 | S3: =SUM(R3:R9802) -> 2261274.8 | T3: =COUNT(R3:R9802) -> 9799 | U3: =IF(R3>=500,"High","Low") -> High
A4: 3 | B4: CA-2017-138688 | C4: 42898 | D4: 42902 | E4: Second Class | F4: DV-13045 | G4: Darrin Van Huff | H4: Corporate | I4: United States | J4: Los Angeles | K4: California | L4: 90036 | M4: West | N4: OFF-LA-10000240 | O4: Office Supplies | P4: Labels | Q4: Self-Adhesive Address Labels for Typewriters by Universal | R4: 14.62 | S4: =SUM(R4:R9803) -> 2260542.9 | T4: =COUNT(R4:R9803) -> 9798 | U4: =IF(R4>=500,"High","Low") -> Low
A5: 4 | B5: US-2016-108966 | C5: 42654 | D5: 42661 | E5: Standard Class | F5: SO-20335 | G5: Sean O'Donnell | H5: Consumer | I5: United States | J5: Fort Lauderdale | K5: Florida | L5: 33311 | M5: South | N5: FUR-TA-10000577 | O5: Furniture | P5: Tables | Q5: Bretford CR4500 Series Slim Rectangular Table | R5: 957.5775 | S5: =SUM(R5:R9804) -> 2260528.3 | T5: =COUNT(R5:R9804) -> 9797 | U5: =IF(R5>=500,"High","Low") -> High
A6: 5 | B6: US-2016-108966 | C6: 42654 | D6: 42661 | E6: Standard Class | F6: SO-20335 | G6: Sean O'Donnell | H6: Consumer | I6: United States | J6: Fort Lauderdale | K6: Florida | L6: 33311 | M6: South | N6: OFF-ST-10000760 | O6: Office Supplies | P6: Storage | Q6: Eldon Fold 'N Roll Cart System | R6: 22.368 | S6: =SUM(R6:R9805) -> 2259570.7 | T6: =COUNT(R6:R9805) -> 9796 | U6: =IF(R6>=500,"High","Low") -> Low
A7: 6 | B7: CA-2015-115812 | C7: 42164 | D7: 42169 | E7: Standard Class | F7: BH-11710 | G7: Brosina Hoffman | H7: Consumer | I7: United States | J7: Los Angeles | K7: California | L7: 90032 | M7: West | N7: FUR-FU-10001487 | O7: Furniture | P7: Furnishings | Q7: Eldon Expressions Wood and Plastic Desk Accessories, Cherry Wood | R7: 48.86 | S7: =SUM(R7:R9806) -> 2259548.3 | T7: =COUNT(R7:R9806) -> 9795 | U7: =IF(R7>=500,"High","Low") -> Low
A8: 7 | B8: CA-2015-115812 | C8: 42164 | D8: 42169 | E8: Standard Class | F8: BH-11710 | G8: Brosina Hoffman | H8: Consumer | I8: United States | J8: Los Angeles | K8: California | L8: 90032 | M8: West | N8: OFF-AR-10002833 | O8: Office Supplies | P8: Art | Q8: Newell 322 | R8: 7.28 | S8: =SUM(R8:R9807) -> 2259499.5 | T8: =COUNT(R8:R9807) -> 9794 | U8: =IF(R8>=500,"High","Low") -> Low
A9: 8 | B9: CA-2015-115812 | C9: 42164 | D9: 42169 | E9: Standard Class | F9: BH-11710 | G9: Brosina Hoffman | H9: Consumer | I9: United States | J9: Los Angeles | K9: California | L9: 90032 | M9: West | N9: TEC-PH-10002275 | O9: Technology | P9: Phones | Q9: Mitel 5320 IP Phone VoIP phone | R9: 907.152 | S9: =SUM(R9:R9808) -> 2259492.2 | T9: =COUNT(R9:R9808) -> 9793 | U9: =IF(R9>=500,"High","Low") -> High
A10: 9 | B10: CA-2015-115812 | C10: 42164 | D10: 42169 | E10: Standard Class | F10: BH-11710 | G10: Brosina Hoffman | H10: Consumer | I10: United States | J10: Los Angeles | K10: California | L10: 90032 | M10: West | N10: OFF-BI-10003910 | O10: Office Supplies | P10: Binders | Q10: DXL Angle-View Binders with Locking Rings by Samsill | R10: 18.504 | S10: =SUM(R10:R9809) -> 2258585 | T10: =COUNT(R10:R9809) -> 9792 | U10: =IF(R10>=500,"High","Low") -> Low
A11: 10 | B11: CA-2015-115812 | C11: 42164 | D11: 42169 | E11: Standard Class | F11: BH-11710 | G11: Brosina Hoffman | H11: Consumer | I11: United States | J11: Los Angeles | K11: California | L11: 90032 | M11: West | N11: OFF-AP-10002892 | O11: Office Supplies | P11: Appliances | Q11: Belkin F5C206VTEL 6 Outlet Surge | R11: 114.9 | S11: =SUM(R11:R9810) -> 2258566.5 | T11: =COUNT(R11:R9810) -> 9791 | U11: =IF(R11>=500,"High","Low") -> Low
A12: 11 | B12: CA-2015-115812 | C12: 42164 | D12: 42169 | E12: Standard Class | F12: BH-11710 | G12: Brosina Hoffman | H12: Consumer | I12: United States | J12: Los Angeles | K12: California | L12: 90032 | M12: West | N12: FUR-TA-10001539 | O12: Furniture | P12: Tables | Q12: Chromcraft Rectangular Conference Tables | R12: 1706.184 | S12: =SUM(R12:R9811) -> 2258451.6 | T12: =COUNT(R12:R9811) -> 9790 | U12: =IF(R12>=500,"High","Low") -> High
A13: 12 | B13: CA-2015-115812 | C13: 42164 | D13: 42169 | E13: Standard Class | F13: BH-11710 | G13: Brosina Hoffman | H13: Consumer | I13: United States | J13: Los Angeles | K13: California | L13: 90032 | M13: West | N13: TEC-PH-10002033 | O13: Technology | P13: Phones | Q13: Konftel 250 ConferenceÂ phoneÂ - Charcoal black | R13: 911.424 | S13: =SUM(R13:R9812) -> 2256745.4 | T13: =COUNT(R13:R9812) -> 9789 | U13: =IF(R13>=500,"High","Low") -> High
... A2235: 2234 | B2235: CA-2016-123232 | C2235: 42718 | D2235: 42720 | E2235: Second Class | F2235: DJ-13630 | G2235: Doug Jacobs | H2235: Consumer | I2235: United States | J2235: Portland | K2235: Oregon | L2235: 97206 | M2235: West | N2235: TEC-PH-10001051 | O2235: Technology | P2235: Phones | Q2235: HTC One | R2235: 319.968 | S2235: =SUM(R2235:R12034) -> 1762199.5 | T2235: =COUNT(R2235:R12034) -> 7567 | U2235: =IF(R2235>=500,"High","Low") -> Low
A2236: 2235 | B2236: CA-2018-104066 | C2236: 43439 | D2236: 43444 | E2236: Standard Class | F2236: QJ-19255 | G2236: Quincy Jones | H2236: Corporate | I2236: United States | J2236: Burlington | K2236: Vermont | M2236: East | N2236: TEC-AC-10001013 | O2236: Technology | P2236: Accessories | Q2236: Logitech ClearChat Comfort/USB Headset H390 | R2236: 205.03 | S2236: =SUM(R2236:R12035) -> 1761879.5 | T2236: =COUNT(R2236:R12035) -> 7566 | U2236: =IF(R2236>=500,"High","Low") -> Low
A2237: 2236 | B2237: CA-2016-145849 | C2237: 42628 | D2237: 42630 | E2237: Second Class | F2237: CT-11995 | G2237: Carol Triggs | H2237: Consumer | I2237: United States | J2237: Indianapolis | K2237: Indiana | L2237: 46203 | M2237: Central | N2237: OFF-ST-10000025 | O2237: Office Supplies | P2237: Storage | Q2237: Fellowes Stor/Drawer Steel Plus Storage Drawers | R2237: 190.86 | S2237: =SUM(R2237:R12036) -> 1761674.5 | T2237: =COUNT(R2237:R12036) -> 7565 | U2237: =IF(R2237>=500,"High","Low") -> Low
A2238: 2237 | B2238: CA-2016-145849 | C2238: 42628 | D2238: 42630 | E2238: Second Class | F2238: CT-11995 | G2238: Carol Triggs | H2238: Consumer | I2238: United States | J2238: Indianapolis | K2238: Indiana | L2238: 46203 | M2238: Central | N2238: OFF-AR-10000817 | O2238: Office Supplies | P2238: Art | Q2238: Manco Dry-Lighter Erasable Highlighter | R2238: 24.32 | S2238: =SUM(R2238:R12037) -> 1761483.6 | T2238: =COUNT(R2238:R12037) -> 7564 | U2238: =IF(R2238>=500,"High","Low") -> Low
A2239: 2238 | B2239: CA-2017-122322 | C2239: 42931 | D2239: 42937 | E2239: Standard Class | F2239: RH-19510 | G2239: Rick Huthwaite | H2239: Home Office | I2239: United States | J2239: Provo | K2239: Utah | L2239: 84604 | M2239: West | N2239: OFF-SU-10000952 | O2239: Office Supplies | P2239: Supplies | Q2239: Fiskars Home & Office Scissors | R2239: 44.4 | S2239: =SUM(R2239:R12038) -> 1761459.3 | T2239: =COUNT(R2239:R12038) -> 7563 | U2239: =IF(R2239>=500,"High","Low") -> Low
A2240: 2239 | B2240: CA-2018-166849 | C2240: 43210 | D2240: 43216 | E2240: Standard Class | F2240: SJ-20125 | G2240: Sanjit Jacobs | H2240: Home Office | I2240: United States | J2240: Chicago | K2240: Illinois | L2240: 60610 | M2240: Central | N2240: FUR-FU-10004597 | O2240: Furniture | P2240: Furnishings | Q2240: Eldon Cleatmat Chair Mats for Medium Pile Carpets | R2240: 44.4 | S2240: =SUM(R2240:R12039) -> 1761414.9 | T2240: =COUNT(R2240:R12039) -> 7562 | U2240: =IF(R2240>=500,"High","Low") -> Low
A2241: 2240 | B2241: CA-2017-146633 | C2241: 43054 | D2241: 43056 | E2241: Second Class | F2241: TG-21310 | G2241: Toby Gnade | H2241: Consumer | I2241: United States | J2241: Los Angeles | K2241: California | L2241: 90049 | M2241: West | N2241: OFF-BI-10003527 | O2241: Office Supplies | P2241: Binders | Q2241: Fellowes PB500 Electric Punch Plastic Comb Binding Machine with Manual Bind | R2241: 1016.792 | S2241: =SUM(R2241:R12040) -> 1761370.5 | T2241: =COUNT(R2241:R12040) -> 7561 | U2241: =IF(R2241>=500,"High","Low") -> High
A2242: 2241 | B2242: CA-2017-146633 | C2242: 43054 | D2242: 43056 | E2242: Second Class | F2242: TG-21310 | G2242: Toby Gnade | H2242: Consumer | I2242: United States | J2242: Los Angeles | K2242: California | L2242: 90049 | M2242: West | N2242: OFF-BI-10002982 | O2242: Office Supplies | P2242: Binders | Q2242: Avery Self-Adhesive Photo Pockets for Polaroid Photos | R2242: 38.136 | S2242: =SUM(R2242:R12041) -> 1760353.7 | T2242: =COUNT(R2242:R12041) -> 7560 | U2242: =IF(R2242>=500,"High","Low") -> Low
A2243: 2242 | B2243: US-2017-126893 | C2243: 43065 | D2243: 43070 | E2243: Standard Class | F2243: CT-11995 | G2243: Carol Triggs | H2243: Consumer | I2243: United States | J2243: Philadelphia | K2243: Pennsylvania | L2243: 19134 | M2243: East | N2243: TEC-PH-10004165 | O2243: Technology | P2243: Phones | Q2243: Mitel MiVoice 5330e IP Phone | R2243: 494.982 | S2243: =SUM(R2243:R12042) -> 1760315.6 | T2243: =COUNT(R2243:R12042) -> 7559 | U2243: =IF(R2243>=500,"High","Low") -> Low
A2244: 2243 | B2244: CA-2018-103380 | C2244: 43425 | D2244: 43429 | E2244: Standard Class | F2244: BF-11005 | G2244: Barry Franz | H2244: Home Office | I2244: United States | J2244: Pasadena | K2244: California | L2244: 91104 | M2244: West | N2244: OFF-ST-10003442 | O2244: Office Supplies | P2244: Storage | Q2244: Eldon Portable Mobile Manager | R2244: 56.56 | S2244: =SUM(R2244:R12043) -> 1759820.6 | T2244: =COUNT(R2244:R12043) -> 7558 | U2244: =IF(R2244>=500,"High","Low") -> Low
A2245: 2244 | B2245: CA-2018-103380 | C2245: 43425 | D2245: 43429 | E2245: Standard Class | F2245: BF-11005 | G2245: Barry Franz | H2245: Home Office | I2245: United States | J2245: Pasadena | K2245: California | L2245: 91104 | M2245: West | N2245: OFF-AR-10003856 | O2245: Office Supplies | P2245: Art | Q2245: Newell 344 | R2245: 5.56 | S2245: =SUM(R2245:R12044) -> 1759764.1 | T2245: =COUNT(R2245:R12044) -> 7557 | U2245: =IF(R2245>=500,"High","Low") -> Low
A2246: 2245 | B2246: CA-2018-103380 | C2246: 43425 | D2246: 43429 | E2246: Standard Class | F2246: BF-11005 | G2246: Barry Franz | H2246: Home Office | I2246: United States | J2246: Pasadena | K2246: California | L2246: 91104 | M2246: West | N2246: OFF-FA-10004248 | O2246: Office Supplies | P2246: Fasteners | Q2246: Advantus T-Pin Paper Clips | R2246: 9.02 | S2246: =SUM(R2246:R12045) -> 1759758.5 | T2246: =COUNT(R2246:R12045) -> 7556 | U2246: =IF(R2246>=500,"High","Low") -> Low
A2247: 2246 | B2247: CA-2018-103380 | C2247: 43425 | D2247: 43429 | E2247: Standard Class | F2247: BF-11005 | G2247: Barry Franz | H2247: Home Office | I2247: United States | J2247: Pasadena | K2247: California | L2247: 91104 | M2247: West | N2247: OFF-AP-10001492 | O2247: Office Supplies | P2247: Appliances | Q2247: Acco Six-Outlet Power Strip, 4' Cord Length | R2247: 8.62 | S2247: =SUM(R2247:R12046) -> 1759749.5 | T2247: =COUNT(R2247:R12046) -> 7555 | U2247: =IF(R2247>=500,"High","Low") -> Low
A2248: 2247 | B2248: CA-2018-103380 | C2248: 43425 | D2248: 43429 | E2248: Standard Class | F2248: BF-11005 | G2248: Barry Franz | H2248: Home Office | I2248: United States | J2248: Pasadena | K2248: California | L2248: 91104 | M2248: West | N2248: TEC-PH-10004165 | O2248: Technology | P2248: Phones | Q2248: Mitel MiVoice 5330e IP Phone | R2248: 659.976 | S2248: =SUM(R2248:R12047) -> 1759740.9 | T2248: =COUNT(R2248:R12047) -> 7554 | U2248: =IF(R2248>=500,"High","Low") -> High
... A5275: 5274 | B5275: US-2017-158309 | C5275: 43065 | D5275: 43068 | E5275: First Class | F5275: PA-19060 | G5275: Pete Armstrong | H5275: Home Office | I5275: United States | J5275: Miami | K5275: Florida | L5275: 33142 | M5275: South | N5275: OFF-BI-10000145 | O5275: Office Supplies | P5275: Binders | Q5275: Zipper Ring Binder Pockets | R5275: 3.744 | S5275: =SUM(R5275:R15074) -> 1056996 | T5275: =COUNT(R5275:R15074) -> 4527 | U5275: =IF(R5275>=500,"High","Low") -> Low
A5276: 5275 | B5276: CA-2016-162887 | C5276: 42681 | D5276: 42683 | E5276: Second Class | F5276: SV-20785 | G5276: Stewart Visinsky | H5276: Consumer | I5276: United States | J5276: Burlington | K5276: Vermont | M5276: East | N5276: FUR-CH-10000595 | O5276: Furniture | P5276: Chairs | Q5276: Safco Contoured Stacking Chairs | R5276: 715.2 | S5276: =SUM(R5276:R15075) -> 1056992.2 | T5276: =COUNT(R5276:R15075) -> 4526 | U5276: =IF(R5276>=500,"High","Low") -> High
A5277: 5276 | B5277: CA-2018-147333 | C5277: 43448 | D5277: 43454 | E5277: Standard Class | F5277: KL-16555 | G5277: Kelly Lampkin | H5277: Corporate | I5277: United States | J5277: Fayetteville | K5277: Arkansas | L5277: 72701 | M5277: South | N5277: TEC-AC-10004469 | O5277: Technology | P5277: Accessories | Q5277: Microsoft Sculpt Comfort Mouse | R5277: 159.8 | S5277: =SUM(R5277:R15076) -> 1056277 | T5277: =COUNT(R5277:R15076) -> 4525 | U5277: =IF(R5277>=500,"High","Low") -> Low
A5278: 5277 | B5278: CA-2018-147333 | C5278: 43448 | D5278: 43454 | E5278: Standard Class | F5278: KL-16555 | G5278: Kelly Lampkin | H5278: Corporate | I5278: United States | J5278: Fayetteville | K5278: Arkansas | L5278: 72701 | M5278: South | N5278: TEC-AC-10003038 | O5278: Technology | P5278: Accessories | Q5278: Kingston Digital DataTraveler 16GB USB 2.0 | R5278: 44.75 | S5278: =SUM(R5278:R15077) -> 1056117.2 | T5278: =COUNT(R5278:R15077) -> 4524 | U5278: =IF(R5278>=500,"High","Low") -> Low
A5279: 5278 | B5279: CA-2015-113859 | C5279: 42260 | D5279: 42264 | E5279: Standard Class | F5279: BC-11125 | G5279: Becky Castell | H5279: Home Office | I5279: United States | J5279: Odessa | K5279: Texas | L5279: 79762 | M5279: Central | N5279: FUR-CH-10004698 | O5279: Furniture | P5279: Chairs | Q5279: Padded Folding Chairs, Black, 4/Carton | R5279: 340.116 | S5279: =SUM(R5279:R15078) -> 1056072.5 | T5279: =COUNT(R5279:R15078) -> 4523 | U5279: =IF(R5279>=500,"High","Low") -> Low
A5280: 5279 | B5280: CA-2015-159681 | C5280: 42345 | D5280: 42351 | E5280: Standard Class | F5280: PO-18850 | G5280: Patrick O'Brill | H5280: Consumer | I5280: United States | J5280: Virginia Beach | K5280: Virginia | L5280: 23464 | M5280: South | N5280: OFF-PA-10003641 | O5280: Office Supplies | P5280: Paper | Q5280: Xerox 1909 | R5280: 105.52 | S5280: =SUM(R5280:R15079) -> 1055732.4 | T5280: =COUNT(R5280:R15079) -> 4522 | U5280: =IF(R5280>=500,"High","Low") -> Low
A5281: 5280 | B5281: US-2018-104094 | C5281: 43350 | D5281: 43354 | E5281: Standard Class | F5281: AG-10675 | G5281: Anna Gayman | H5281: Consumer | I5281: United States | J5281: Milwaukee | K5281: Wisconsin | L5281: 53209 | M5281: Central | N5281: TEC-AC-10002134 | O5281: Technology | P5281: Accessories | Q5281: Rosewill 107 Normal Keys USB Wired Standard Keyboard | R5281: 13.48 | S5281: =SUM(R5281:R15080) -> 1055626.8 | T5281: =COUNT(R5281:R15080) -> 4521 | U5281: =IF(R5281>=500,"High","Low") -> Low
A5282: 5281 | B5282: CA-2018-152709 | C5282: 43380 | D5282: 43385 | E5282: Standard Class | F5282: DB-13210 | G5282: Dean Braden | H5282: Consumer | I5282: United States | J5282: Detroit | K5282: Michigan | L5282: 48234 | M5282: Central | N5282: OFF-ST-10001837 | O5282: Office Supplies | P5282: Storage | Q5282: SAFCO Mobile Desk Side File, Wire Frame | R5282: 85.52 | S5282: =SUM(R5282:R15081) -> 1055613.4 | T5282: =COUNT(R5282:R15081) -> 4520 | U5282: =IF(R5282>=500,"High","Low") -> Low
A5283: 5282 | B5283: CA-2016-105158 | C5283: 42618 | D5283: 42623 | E5283: Standard Class | F5283: SP-20860 | G5283: Sung Pak | H5283: Corporate | I5283: United States | J5283: Rochester | K5283: Minnesota | L5283: 55901 | M5283: Central | N5283: FUR-FU-10001706 | O5283: Furniture | P5283: Furnishings | Q5283: Longer-Life Soft White Bulbs | R5283: 6.16 | S5283: =SUM(R5283:R15082) -> 1055527.8 | T5283: =COUNT(R5283:R15082) -> 4519 | U5283: =IF(R5283>=500,"High","Low") -> Low
A5284: 5283 | B5284: CA-2016-105158 | C5284: 42618 | D5284: 42623 | E5284: Standard Class | F5284: SP-20860 | G5284: Sung Pak | H5284: Corporate | I5284: United States | J5284: Rochester | K5284: Minnesota | L5284: 55901 | M5284: Central | N5284: OFF-PA-10001970 | O5284: Office Supplies | P5284: Paper | Q5284: Xerox 1881 | R5284: 36.84 | S5284: =SUM(R5284:R15083) -> 1055521.7 | T5284: =COUNT(R5284:R15083) -> 4518 | U5284: =IF(R5284>=500,"High","Low") -> Low
A5285: 5284 | B5285: CA-2015-133424 | C5285: 42093 | D5285: 42098 | E5285: Standard Class | F5285: Dl-13600 | G5285: Dorris liebe | H5285: Corporate | I5285: United States | J5285: Seattle | K5285: Washington | L5285: 98105 | M5285: West | N5285: OFF-ST-10002957 | O5285: Office Supplies | P5285: Storage | Q5285: Sterilite Show Offs Storage Containers | R5285: 15.84 | S5285: =SUM(R5285:R15084) -> 1055484.8 | T5285: =COUNT(R5285:R15084) -> 4517 | U5285: =IF(R5285>=500,"High","Low") -> Low
A5286: 5285 | B5286: CA-2015-133424 | C5286: 42093 | D5286: 42098 | E5286: Standard Class | F5286: Dl-13600 | G5286: Dorris liebe | H5286: Corporate | I5286: United States | J5286: Seattle | K5286: Washington | L5286: 98105 | M5286: West | N5286: OFF-LA-10002312 | O5286: Office Supplies | P5286: Labels | Q5286: Avery 490 | R5286: 44.4 | S5286: =SUM(R5286:R15085) -> 1055469 | T5286: =COUNT(R5286:R15085) -> 4516 | U5286: =IF(R5286>=500,"High","Low") -> Low
A5287: 5286 | B5287: CA-2018-105991 | C5287: 43225 | D5287: 43226 | E5287: First Class | F5287: LH-17020 | G5287: Lisa Hazard | H5287: Consumer | I5287: United States | J5287: Louisville | K5287: Colorado | L5287: 80027 | M5287: West | N5287: OFF-EN-10002600 | O5287: Office Supplies | P5287: Envelopes | Q5287: Redi-Strip #10 Envelopes, 4 1/8 x 9 1/2 | R5287: 21.24 | S5287: =SUM(R5287:R15086) -> 1055424.6 | T5287: =COUNT(R5287:R15086) -> 4515 | U5287: =IF(R5287>=500,"High","Low") -> Low
A5288: 5287 | B5288: CA-2018-105991 | C5288: 43225 | D5288: 43226 | E5288: First Class | F5288: LH-17020 | G5288: Lisa Hazard | H5288: Consumer | I5288: United States | J5288: Louisville | K5288: Colorado | L5288: 80027 | M5288: West | N5288: OFF-BI-10003274 | O5288: Office Supplies | P5288: Binders | Q5288: Avery Durable Slant Ring Binders, No Labels | R5288: 9.552 | S5288: =SUM(R5288:R15087) -> 1055403.4 | T5288: =COUNT(R5288:R15087) -> 4514 | U5288: =IF(R5288>=500,"High","Low") -> Low
... A8799: 8798 | B8799: CA-2017-106397 | C8799: 42923 | D8799: 42929 | E8799: Standard Class | F8799: MJ-17740 | G8799: Max Jones | H8799: Consumer | I8799: United States | J8799: Orem | K8799: Utah | L8799: 84057 | M8799: West | N8799: OFF-AR-10004602 | O8799: Office Supplies | P8799: Art | Q8799: Boston KS Multi-Size Manual Pencil Sharpener | R8799: 45.98 | S8799: =SUM(R8799:R18598) -> 234781.52 | T8799: =COUNT(R8799:R18598) -> 1003 | U8799: =IF(R8799>=500,"High","Low") -> Low
A8800: 8799 | B8800: US-2017-150140 | C8800: 42831 | D8800: 42835 | E8800: Standard Class | F8800: VM-21685 | G8800: Valerie Mitchum | H8800: Home Office | I8800: United States | J8800: Burlington | K8800: Vermont | M8800: East | N8800: TEC-PH-10002555 | O8800: Technology | P8800: Phones | Q8800: Nortel Meridian M5316 Digital phone | R8800: 1294.75 | S8800: =SUM(R8800:R18599) -> 234735.54 | T8800: =COUNT(R8800:R18599) -> 1002 | U8800: =IF(R8800>=500,"High","Low") -> High
A8801: 8800 | B8801: CA-2015-116666 | C8801: 42132 | D8801: 42134 | E8801: First Class | F8801: KT-16480 | G8801: Kean Thornton | H8801: Consumer | I8801: United States | J8801: Philadelphia | K8801: Pennsylvania | L8801: 19134 | M8801: East | N8801: TEC-CO-10001449 | O8801: Technology | P8801: Copiers | Q8801: Hewlett Packard LaserJet 3310 Copier | R8801: 1799.97 | S8801: =SUM(R8801:R18600) -> 233440.79 | T8801: =COUNT(R8801:R18600) -> 1001 | U8801: =IF(R8801>=500,"High","Low") -> High
A8802: 8801 | B8802: CA-2018-148992 | C8802: 43427 | D8802: 43431 | E8802: Standard Class | F8802: CS-12250 | G8802: Chris Selesnick | H8802: Corporate | I8802: United States | J8802: Chicago | K8802: Illinois | L8802: 60623 | M8802: Central | N8802: OFF-PA-10004285 | O8802: Office Supplies | P8802: Paper | Q8802: Xerox 1959 | R8802: 10.688 | S8802: =SUM(R8802:R18601) -> 231640.82 | T8802: =COUNT(R8802:R18601) -> 1000 | U8802: =IF(R8802>=500,"High","Low") -> Low
A8803: 8802 | B8803: CA-2017-140935 | C8803: 43049 | D8803: 43051 | E8803: First Class | F8803: AB-10015 | G8803: Aaron Bergman | H8803: Consumer | I8803: United States | J8803: Oklahoma City | K8803: Oklahoma | L8803: 73120 | M8803: Central | N8803: TEC-PH-10000562 | O8803: Technology | P8803: Phones | Q8803: Samsung Convoy 3 | R8803: 221.98 | S8803: =SUM(R8803:R18602) -> 231630.13 | T8803: =COUNT(R8803:R18602) -> 999 | U8803: =IF(R8803>=500,"High","Low") -> Low
A8804: 8803 | B8804: CA-2017-140935 | C8804: 43049 | D8804: 43051 | E8804: First Class | F8804: AB-10015 | G8804: Aaron Bergman | H8804: Consumer | I8804: United States | J8804: Oklahoma City | K8804: Oklahoma | L8804: 73120 | M8804: Central | N8804: FUR-BO-10003966 | O8804: Furniture | P8804: Bookcases | Q8804: Sauder Facets Collection Library, Sky Alder Finish | R8804: 341.96 | S8804: =SUM(R8804:R18603) -> 231408.15 | T8804: =COUNT(R8804:R18603) -> 998 | U8804: =IF(R8804>=500,"High","Low") -> Low
A8805: 8804 | B8805: CA-2015-157644 | C8805: 42369 | D8805: 42370 | E8805: First Class | F8805: AH-10030 | G8805: Aaron Hawkins | H8805: Corporate | I8805: United States | J8805: New York City | K8805: New York | L8805: 10035 | M8805: East | N8805: TEC-AC-10003614 | O8805: Technology | P8805: Accessories | Q8805: Verbatim 25 GB 6x Blu-ray Single Layer Recordable Disc, 10/Pack | R8805: 34.77 | S8805: =SUM(R8805:R18604) -> 231066.19 | T8805: =COUNT(R8805:R18604) -> 997 | U8805: =IF(R8805>=500,"High","Low") -> Low
A8806: 8805 | B8806: CA-2015-157644 | C8806: 42369 | D8806: 42370 | E8806: First Class | F8806: AH-10030 | G8806: Aaron Hawkins | H8806: Corporate | I8806: United States | J8806: New York City | K8806: New York | L8806: 10035 | M8806: East | N8806: OFF-LA-10003148 | O8806: Office Supplies | P8806: Labels | Q8806: Avery 51 | R8806: 18.9 | S8806: =SUM(R8806:R18605) -> 231031.42 | T8806: =COUNT(R8806:R18605) -> 996 | U8806: =IF(R8806>=500,"High","Low") -> Low
A8807: 8806 | B8807: US-2018-100398 | C8807: 43331 | D8807: 43335 | E8807: Standard Class | F8807: DO-13435 | G8807: Denny Ordway | H8807: Consumer | I8807: United States | J8807: Salt Lake City | K8807: Utah | L8807: 84106 | M8807: West | N8807: OFF-BI-10002133 | O8807: Office Supplies | P8807: Binders | Q8807: Wilson Jones Elliptical Ring 3 1/2" Capacity Binders, 800 sheets | R8807: 102.72 | S8807: =SUM(R8807:R18606) -> 231012.52 | T8807: =COUNT(R8807:R18606) -> 995 | U8807: =IF(R8807>=500,"High","Low") -> Low
A8808: 8807 | B8808: CA-2017-113082 | C8808: 42990 | D8808: 42994 | E8808: Standard Class | F8808: MC-17590 | G8808: Matt Collister | H8808: Corporate | I8808: United States | J8808: Utica | K8808: New York | L8808: 13501 | M8808: East | N8808: FUR-FU-10002813 | O8808: Furniture | P8808: Furnishings | Q8808: DAX Contemporary Wood Frame with Silver Metal Mat, Desktop, 11 x 14 Size | R8808: 40.48 | S8808: =SUM(R8808:R18607) -> 230909.8 | T8808: =COUNT(R8808:R18607) -> 994 | U8808: =IF(R8808>=500,"High","Low") -> Low
A8809: 8808 | B8809: US-2018-110646 | C8809: 43399 | D8809: 43404 | E8809: Standard Class | F8809: JF-15190 | G8809: Jamie Frazer | H8809: Consumer | I8809: United States | J8809: Philadelphia | K8809: Pennsylvania | L8809: 19134 | M8809: East | N8809: OFF-BI-10004330 | O8809: Office Supplies | P8809: Binders | Q8809: GBC Velobind Prepunched Cover Sets, Regency Series | R8809: 33.282 | S8809: =SUM(R8809:R18608) -> 230869.32 | T8809: =COUNT(R8809:R18608) -> 993 | U8809: =IF(R8809>=500,"High","Low") -> Low
A8810: 8809 | B8810: US-2018-110646 | C8810: 43399 | D8810: 43404 | E8810: Standard Class | F8810: JF-15190 | G8810: Jamie Frazer | H8810: Consumer | I8810: United States | J8810: Philadelphia | K8810: Pennsylvania | L8810: 19134 | M8810: East | N8810: TEC-PH-10002807 | O8810: Technology | P8810: Phones | Q8810: Motorla HX550 Universal Bluetooth Headset | R8810: 118.65 | S8810: =SUM(R8810:R18609) -> 230836.04 | T8810: =COUNT(R8810:R18609) -> 992 | U8810: =IF(R8810>=500,"High","Low") -> Low
A8811: 8810 | B8811: US-2018-110646 | C8811: 43399 | D8811: 43404 | E8811: Standard Class | F8811: JF-15190 | G8811: Jamie Frazer | H8811: Consumer | I8811: United States | J8811: Philadelphia | K8811: Pennsylvania | L8811: 19134 | M8811: East | N8811: OFF-LA-10001404 | O8811: Office Supplies | P8811: Labels | Q8811: Avery 517 | R8811: 14.76 | S8811: =SUM(R8811:R18610) -> 230717.39 | T8811: =COUNT(R8811:R18610) -> 991 | U8811: =IF(R8811>=500,"High","Low") -> Low
A8812: 8811 | B8812: CA-2018-120614 | C8812: 43250 | D8812: 43255 | E8812: Standard Class | F8812: SM-20950 | G8812: Suzanne McNair | H8812: Corporate | I8812: United States | J8812: Los Angeles | K8812: California | L8812: 90004 | M8812: West | N8812: OFF-PA-10004911 | O8812: Office Supplies | P8812: Paper | Q8812: Rediform S.O.S. 1-Up Phone Message Bk, 4-1/4x3-1/16 Bk, 1 Form/Pg, 40 Messages/Bk, 3/Pk | R8812: 37.52 | S8812: =SUM(R8812:R18611) -> 230702.63 | T8812: =COUNT(R8812:R18611) -> 990 | U8812: =IF(R8812>=500,"High","Low") -> Low
... A9147: 9146 | B9147: CA-2016-126970 | C9147: 42633 | D9147: 42637 | E9147: Standard Class | F9147: TP-21130 | G9147: Theone Pippenger | H9147: Consumer | I9147: United States | J9147: Naperville | K9147: Illinois | L9147: 60540 | M9147: Central | N9147: OFF-BI-10000138 | O9147: Office Supplies | P9147: Binders | Q9147: Acco Translucent Poly Ring Binders | R9147: 2.808 | S9147: =SUM(R9147:R18946) -> 151334.96 | T9147: =COUNT(R9147:R18946) -> 655 | U9147: =IF(R9147>=500,"High","Low") -> Low
A9148: 9147 | B9148: US-2017-165505 | C9148: 42758 | D9148: 42762 | E9148: Standard Class | F9148: CB-12535 | G9148: Claudia Bergmann | H9148: Corporate | I9148: United States | J9148: Burlington | K9148: Vermont | M9148: East | N9148: TEC-AC-10002926 | O9148: Technology | P9148: Accessories | Q9148: Logitech Wireless Marathon Mouse M705 | R9148: 99.98 | S9148: =SUM(R9148:R18947) -> 151332.15 | T9148: =COUNT(R9148:R18947) -> 654 | U9148: =IF(R9148>=500,"High","Low") -> Low
A9149: 9148 | B9149: US-2017-165505 | C9149: 42758 | D9149: 42762 | E9149: Standard Class | F9149: CB-12535 | G9149: Claudia Bergmann | H9149: Corporate | I9149: United States | J9149: Burlington | K9149: Vermont | M9149: East | N9149: OFF-AR-10003477 | O9149: Office Supplies | P9149: Art | Q9149: 4009 Highlighters | R9149: 8.04 | S9149: =SUM(R9149:R18948) -> 151232.17 | T9149: =COUNT(R9149:R18948) -> 653 | U9149: =IF(R9149>=500,"High","Low") -> Low
A9150: 9149 | B9150: US-2017-165505 | C9150: 42758 | D9150: 42762 | E9150: Standard Class | F9150: CB-12535 | G9150: Claudia Bergmann | H9150: Corporate | I9150: United States | J9150: Burlington | K9150: Vermont | M9150: East | N9150: OFF-ST-10001526 | O9150: Office Supplies | P9150: Storage | Q9150: Iceberg Mobile Mega Data/Printer Cart | R9150: 1564.29 | S9150: =SUM(R9150:R18949) -> 151224.13 | T9150: =COUNT(R9150:R18949) -> 652 | U9150: =IF(R9150>=500,"High","Low") -> High
A9151: 9150 | B9151: US-2015-157070 | C9151: 42156 | D9151: 42161 | E9151: Standard Class | F9151: QJ-19255 | G9151: Quincy Jones | H9151: Corporate | I9151: United States | J9151: Detroit | K9151: Michigan | L9151: 48234 | M9151: Central | N9151: OFF-BI-10001765 | O9151: Office Supplies | P9151: Binders | Q9151: Wilson Jones Heavy-Duty Casebound Ring Binders with Metal Hinges | R9151: 138.56 | S9151: =SUM(R9151:R18950) -> 149659.84 | T9151: =COUNT(R9151:R18950) -> 651 | U9151: =IF(R9151>=500,"High","Low") -> Low
A9152: 9151 | B9152: US-2015-157070 | C9152: 42156 | D9152: 42161 | E9152: Standard Class | F9152: QJ-19255 | G9152: Quincy Jones | H9152: Corporate | I9152: United States | J9152: Detroit | K9152: Michigan | L9152: 48234 | M9152: Central | N9152: OFF-AP-10004859 | O9152: Office Supplies | P9152: Appliances | Q9152: Acco 6 Outlet Guardian Premium Surge Suppressor | R9152: 65.52 | S9152: =SUM(R9152:R18951) -> 149521.28 | T9152: =COUNT(R9152:R18951) -> 650 | U9152: =IF(R9152>=500,"High","Low") -> Low
A9153: 9152 | B9153: US-2016-106873 | C9153: 42637 | D9153: 42642 | E9153: Second Class | F9153: KM-16720 | G9153: Kunst Miller | H9153: Consumer | I9153: United States | J9153: Avondale | K9153: Arizona | L9153: 85323 | M9153: West | N9153: OFF-AR-10003179 | O9153: Office Supplies | P9153: Art | Q9153: Dixon Ticonderoga Core-Lock Colored Pencils | R9153: 14.576 | S9153: =SUM(R9153:R18952) -> 149455.76 | T9153: =COUNT(R9153:R18952) -> 649 | U9153: =IF(R9153>=500,"High","Low") -> Low
A9154: 9153 | B9154: US-2016-106873 | C9154: 42637 | D9154: 42642 | E9154: Second Class | F9154: KM-16720 | G9154: Kunst Miller | H9154: Consumer | I9154: United States | J9154: Avondale | K9154: Arizona | L9154: 85323 | M9154: West | N9154: TEC-AC-10002345 | O9154: Technology | P9154: Accessories | Q9154: HP Standard 104 key PS/2 Keyboard | R9154: 23.2 | S9154: =SUM(R9154:R18953) -> 149441.19 | T9154: =COUNT(R9154:R18953) -> 648 | U9154: =IF(R9154>=500,"High","Low") -> Low
A9155: 9154 | B9155: US-2016-106873 | C9155: 42637 | D9155: 42642 | E9155: Second Class | F9155: KM-16720 | G9155: Kunst Miller | H9155: Consumer | I9155: United States | J9155: Avondale | K9155: Arizona | L9155: 85323 | M9155: West | N9155: OFF-AR-10001246 | O9155: Office Supplies | P9155: Art | Q9155: Newell 317 | R9155: 16.464 | S9155: =SUM(R9155:R18954) -> 149417.99 | T9155: =COUNT(R9155:R18954) -> 647 | U9155: =IF(R9155>=500,"High","Low") -> Low
A9156: 9155 | B9156: CA-2017-132990 | C9156: 42948 | D9156: 42950 | E9156: Second Class | F9156: KM-16660 | G9156: Khloe Miller | H9156: Consumer | I9156: United States | J9156: Philadelphia | K9156: Pennsylvania | L9156: 19140 | M9156: East | N9156: FUR-FU-10004864 | O9156: Furniture | P9156: Furnishings | Q9156: Eldon 500 Class Desk Accessories | R9156: 19.312 | S9156: =SUM(R9156:R18955) -> 149401.52 | T9156: =COUNT(R9156:R18955) -> 646 | U9156: =IF(R9156>=500,"High","Low") -> Low
A9157: 9156 | B9157: CA-2015-102645 | C9157: 42027 | D9157: 42032 | E9157: Standard Class | F9157: IM-15055 | G9157: Ionia McGrath | H9157: Consumer | I9157: United States | J9157: Las Vegas | K9157: Nevada | L9157: 89115 | M9157: West | N9157: OFF-PA-10001804 | O9157: Office Supplies | P9157: Paper | Q9157: Xerox 195 | R9157: 40.08 | S9157: =SUM(R9157:R18956) -> 149382.21 | T9157: =COUNT(R9157:R18956) -> 645 | U9157: =IF(R9157>=500,"High","Low") -> Low
A9158: 9157 | B9158: CA-2015-134215 | C9158: 42220 | D9158: 42224 | E9158: Standard Class | F9158: ML-17395 | G9158: Marina Lichtenstein | H9158: Corporate | I9158: United States | J9158: Bangor | K9158: Maine | L9158: 4401 | M9158: East | N9158: OFF-AP-10001271 | O9158: Office Supplies | P9158: Appliances | Q9158: Eureka The Boss Cordless Rechargeable Stick Vac | R9158: 101.96 | S9158: =SUM(R9158:R18957) -> 149342.13 | T9158: =COUNT(R9158:R18957) -> 644 | U9158: =IF(R9158>=500,"High","Low") -> Low
A9159: 9158 | B9159: CA-2015-134215 | C9159: 42220 | D9159: 42224 | E9159: Standard Class | F9159: ML-17395 | G9159: Marina Lichtenstein | H9159: Corporate | I9159: United States | J9159: Bangor | K9159: Maine | L9159: 4401 | M9159: East | N9159: OFF-PA-10004353 | O9159: Office Supplies | P9159: Paper | Q9159: Southworth 25% Cotton Premium Laser Paper and Envelopes | R9159: 259.74 | S9159: =SUM(R9159:R18958) -> 149240.17 | T9159: =COUNT(R9159:R18958) -> 643 | U9159: =IF(R9159>=500,"High","Low") -> Low
A9160: 9159 | B9160: CA-2015-134215 | C9160: 42220 | D9160: 42224 | E9160: Standard Class | F9160: ML-17395 | G9160: Marina Lichtenstein | H9160: Corporate | I9160: United States | J9160: Bangor | K9160: Maine | L9160: 4401 | M9160: East | N9160: TEC-AC-10002473 | O9160: Technology | P9160: Accessories | Q9160: Maxell 4.7GB DVD-R | R9160: 255.42 | S9160: =SUM(R9160:R18959) -> 148980.43 | T9160: =COUNT(R9160:R18959) -> 642 | U9160: =IF(R9160>=500,"High","Low") -> Low
A9161: 9160 | B9161: CA-2017-118934 | C9161: 42956 | D9161: 42961 | E9161: Standard Class | F9161: GH-14410 | G9161: Gary Hansen | H9161: Home Office | I9161: United States | J9161: Hendersonville | K9161: Tennessee | L9161: 37075 | M9161: South | N9161: OFF-BI-10003314 | O9161: Office Supplies | P9161: Binders | Q9161: Tuff Stuff Recycled Round Ring Binders | R9161: 4.338 | S9161: =SUM(R9161:R18960) -> 148725.01 | T9161: =COUNT(R9161:R18960) -> 641 | U9161: =IF(R9161>=500,"High","Low") -> Low
A9162: 9161 | B9162: CA-2017-118934 | C9162: 42956 | D9162: 42961 | E9162: Standard Class | F9162: GH-14410 | G9162: Gary Hansen | H9162: Home Office | I9162: United States | J9162: Hendersonville | K9162: Tennessee | L9162: 37075 | M9162: South | N9162: OFF-BI-10004465 | O9162: Office Supplies | P9162: Binders | Q9162: Avery Durable Slant Ring Binders | R9162: 11.88 | S9162: =SUM(R9162:R18961) -> 148720.67 | T9162: =COUNT(R9162:R18961) -> 640 | U9162: =IF(R9162>=500,"High","Low") -> Low
... A9387: 9386 | B9387: CA-2018-163097 | C9387: 43339 | D9387: 43343 | E9387: Standard Class | F9387: SF-20200 | G9387: Sarah Foster | H9387: Consumer | I9387: United States | J9387: Mesa | K9387: Arizona | L9387: 85204 | M9387: West | N9387: FUR-FU-10004973 | O9387: Furniture | P9387: Furnishings | Q9387: Flat Face Poster Frame | R9387: 120.576 | S9387: =SUM(R9387:R19186) -> 101624.21 | T9387: =COUNT(R9387:R19186) -> 415 | U9387: =IF(R9387>=500,"High","Low") -> Low
A9388: 9387 | B9388: US-2018-127292 | C9388: 43119 | D9388: 43123 | E9388: Standard Class | F9388: RM-19375 | G9388: Raymond Messe | H9388: Consumer | I9388: United States | J9388: Burlington | K9388: Vermont | M9388: East | N9388: OFF-PA-10000157 | O9388: Office Supplies | P9388: Paper | Q9388: Xerox 191 | R9388: 79.92 | S9388: =SUM(R9388:R19187) -> 101503.63 | T9388: =COUNT(R9388:R19187) -> 414 | U9388: =IF(R9388>=500,"High","Low") -> Low
A9389: 9388 | B9389: US-2018-127292 | C9389: 43119 | D9389: 43123 | E9389: Standard Class | F9389: RM-19375 | G9389: Raymond Messe | H9389: Consumer | I9389: United States | J9389: Burlington | K9389: Vermont | M9389: East | N9389: OFF-PA-10001970 | O9389: Office Supplies | P9389: Paper | Q9389: Xerox 1881 | R9389: 12.28 | S9389: =SUM(R9389:R19188) -> 101423.71 | T9389: =COUNT(R9389:R19188) -> 413 | U9389: =IF(R9389>=500,"High","Low") -> Low
A9390: 9389 | B9390: US-2018-127292 | C9390: 43119 | D9390: 43123 | E9390: Standard Class | F9390: RM-19375 | G9390: Raymond Messe | H9390: Consumer | I9390: United States | J9390: Burlington | K9390: Vermont | M9390: East | N9390: OFF-AP-10000828 | O9390: Office Supplies | P9390: Appliances | Q9390: Avanti 4.4 Cu. Ft. Refrigerator | R9390: 542.94 | S9390: =SUM(R9390:R19189) -> 101411.43 | T9390: =COUNT(R9390:R19189) -> 412 | U9390: =IF(R9390>=500,"High","Low") -> High
A9391: 9390 | B9391: US-2018-127292 | C9391: 43119 | D9391: 43123 | E9391: Standard Class | F9391: RM-19375 | G9391: Raymond Messe | H9391: Consumer | I9391: United States | J9391: Burlington | K9391: Vermont | M9391: East | N9391: OFF-EN-10001509 | O9391: Office Supplies | P9391: Envelopes | Q9391: Poly String Tie Envelopes | R9391: 2.04 | S9391: =SUM(R9391:R19190) -> 100868.49 | T9391: =COUNT(R9391:R19190) -> 411 | U9391: =IF(R9391>=500,"High","Low") -> Low
A9392: 9391 | B9392: CA-2016-163734 | C9392: 42540 | D9392: 42545 | E9392: Standard Class | F9392: KM-16375 | G9392: Katherine Murray | H9392: Home Office | I9392: United States | J9392: Houston | K9392: Texas | L9392: 77070 | M9392: Central | N9392: OFF-ST-10003692 | O9392: Office Supplies | P9392: Storage | Q9392: Recycled Steel Personal File for Hanging File Folders | R9392: 228.92 | S9392: =SUM(R9392:R19191) -> 100866.45 | T9392: =COUNT(R9392:R19191) -> 410 | U9392: =IF(R9392>=500,"High","Low") -> Low
A9393: 9392 | B9393: CA-2018-162474 | C9393: 43172 | D9393: 43175 | E9393: First Class | F9393: FH-14275 | G9393: Frank Hawley | H9393: Corporate | I9393: United States | J9393: Aurora | K9393: Illinois | L9393: 60505 | M9393: Central | N9393: TEC-PH-10004700 | O9393: Technology | P9393: Phones | Q9393: PowerGen Dual USB Car Charger | R9393: 7.992 | S9393: =SUM(R9393:R19192) -> 100637.53 | T9393: =COUNT(R9393:R19192) -> 409 | U9393: =IF(R9393>=500,"High","Low") -> Low
A9394: 9393 | B9394: CA-2016-130848 | C9394: 42668 | D9394: 42668 | E9394: Same Day | F9394: DG-13300 | G9394: Deirdre Greer | H9394: Corporate | I9394: United States | J9394: Denver | K9394: Colorado | L9394: 80219 | M9394: West | N9394: FUR-CH-10000422 | O9394: Furniture | P9394: Chairs | Q9394: Global Highback Leather Tilter in Burgundy | R9394: 582.336 | S9394: =SUM(R9394:R19193) -> 100629.54 | T9394: =COUNT(R9394:R19193) -> 408 | U9394: =IF(R9394>=500,"High","Low") -> High
A9395: 9394 | B9395: CA-2015-125997 | C9395: 42267 | D9395: 42270 | E9395: First Class | F9395: MW-18220 | G9395: Mitch Webber | H9395: Consumer | I9395: United States | J9395: New York City | K9395: New York | L9395: 10011 | M9395: East | N9395: TEC-PH-10003484 | O9395: Technology | P9395: Phones | Q9395: Ooma Telo VoIP Home Phone System | R9395: 629.95 | S9395: =SUM(R9395:R19194) -> 100047.21 | T9395: =COUNT(R9395:R19194) -> 407 | U9395: =IF(R9395>=500,"High","Low") -> High
A9396: 9395 | B9396: CA-2015-125997 | C9396: 42267 | D9396: 42270 | E9396: First Class | F9396: MW-18220 | G9396: Mitch Webber | H9396: Consumer | I9396: United States | J9396: New York City | K9396: New York | L9396: 10011 | M9396: East | N9396: FUR-CH-10001394 | O9396: Furniture | P9396: Chairs | Q9396: Global Leather Executive Chair | R9396: 631.782 | S9396: =SUM(R9396:R19195) -> 99417.257 | T9396: =COUNT(R9396:R19195) -> 406 | U9396: =IF(R9396>=500,"High","Low") -> High
A9397: 9396 | B9397: CA-2015-125997 | C9397: 42267 | D9397: 42270 | E9397: First Class | F9397: MW-18220 | G9397: Mitch Webber | H9397: Consumer | I9397: United States | J9397: New York City | K9397: New York | L9397: 10011 | M9397: East | N9397: FUR-BO-10002213 | O9397: Furniture | P9397: Bookcases | Q9397: DMI Eclipse Executive Suite Bookcases | R9397: 801.568 | S9397: =SUM(R9397:R19196) -> 98785.475 | T9397: =COUNT(R9397:R19196) -> 405 | U9397: =IF(R9397>=500,"High","Low") -> High
A9398: 9397 | B9398: CA-2015-125997 | C9398: 42267 | D9398: 42270 | E9398: First Class | F9398: MW-18220 | G9398: Mitch Webber | H9398: Consumer | I9398: United States | J9398: New York City | K9398: New York | L9398: 10011 | M9398: East | N9398: OFF-LA-10002762 | O9398: Office Supplies | P9398: Labels | Q9398: Avery 485 | R9398: 75.18 | S9398: =SUM(R9398:R19197) -> 97983.907 | T9398: =COUNT(R9398:R19197) -> 404 | U9398: =IF(R9398>=500,"High","Low") -> Low
A9399: 9398 | B9399: CA-2015-125997 | C9399: 42267 | D9399: 42270 | E9399: First Class | F9399: MW-18220 | G9399: Mitch Webber | H9399: Consumer | I9399: United States | J9399: New York City | K9399: New York | L9399: 10011 | M9399: East | N9399: OFF-AP-10003842 | O9399: Office Supplies | P9399: Appliances | Q9399: Euro-Pro Shark Turbo Vacuum | R9399: 30.98 | S9399: =SUM(R9399:R19198) -> 97908.727 | T9399: =COUNT(R9399:R19198) -> 403 | U9399: =IF(R9399>=500,"High","Low") -> Low
A9400: 9399 | B9400: CA-2015-125997 | C9400: 42267 | D9400: 42270 | E9400: First Class | F9400: MW-18220 | G9400: Mitch Webber | H9400: Consumer | I9400: United States | J9400: New York City | K9400: New York | L9400: 10011 | M9400: East | N9400: TEC-PH-10003072 | O9400: Technology | P9400: Phones | Q9400: Panasonic KX-TG9541B DECT 6.0 Digital 2-Line Expandable Cordless Phone With Digital Answering System | R9400: 1349.91 | S9400: =SUM(R9400:R19199) -> 97877.747 | T9400: =COUNT(R9400:R19199) -> 402 | U9400: =IF(R9400>=500,"High","Low") -> High
A9401: 9400 | B9401: CA-2017-103128 | C9401: 43050 | D9401: 43054 | E9401: Standard Class | F9401: SC-20845 | G9401: Sung Chung | H9401: Consumer | I9401: United States | J9401: Arlington Heights | K9401: Illinois | L9401: 60004 | M9401: Central | N9401: OFF-AR-10003394 | O9401: Office Supplies | P9401: Art | Q9401: Newell 332 | R9401: 14.112 | S9401: =SUM(R9401:R19200) -> 96527.837 | T9401: =COUNT(R9401:R19200) -> 401 | U9401: =IF(R9401>=500,"High","Low") -> Low
A9402: 9401 | B9402: CA-2016-167696 | C9402: 42629 | D9402: 42634 | E9402: Standard Class | F9402: BD-11500 | G9402: Bradley Drucker | H9402: Consumer | I9402: United States | J9402: Newport News | K9402: Virginia | L9402: 23602 | M9402: South | N9402: OFF-EN-10001539 | O9402: Office Supplies | P9402: Envelopes | Q9402: Staple envelope | R9402: 31.12 | S9402: =SUM(R9402:R19201) -> 96513.725 | T9402: =COUNT(R9402:R19201) -> 400 | U9402: =IF(R9402>=500,"High","Low") -> Low
A9403: 9402 | B9403: CA-2015-159814 | C9403: 42179 | D9403: 42183 | E9403: Standard Class | F9403: LP-17080 | G9403: Liz Pelletier | H9403: Consumer | I9403: United States | J9403: Tucson | K9403: Arizona | L9403: 85705 | M9403: West | N9403: FUR-FU-10001731 | O9403: Furniture | P9403: Furnishings | Q9403: Acrylic Self-Standing Desk Frames | R9403: 4.272 | S9403: =SUM(R9403:R19202) -> 96482.605 | T9403: =COUNT(R9403:R19202) -> 399 | U9403: =IF(R9403>=500,"High","Low") -> Low
... A9742: 9741 | B9742: CA-2018-129294 | C9742: 43175 | D9742: 43180 | E9742: Standard Class | F9742: KD-16615 | G9742: Ken Dana | H9742: Corporate | I9742: United States | J9742: Los Angeles | K9742: California | L9742: 90032 | M9742: West | N9742: OFF-AP-10001154 | O9742: Office Supplies | P9742: Appliances | Q9742: Bionaire Personal Warm Mist Humidifier/Vaporizer | R9742: 140.67 | S9742: =SUM(R9742:R19541) -> 16744.768 | T9742: =COUNT(R9742:R19541) -> 60 | U9742: =IF(R9742>=500,"High","Low") -> Low
A9743: 9742 | B9743: CA-2016-117086 | C9743: 42682 | D9743: 42686 | E9743: Standard Class | F9743: QJ-19255 | G9743: Quincy Jones | H9743: Corporate | I9743: United States | J9743: Burlington | K9743: Vermont | M9743: East | N9743: FUR-BO-10004834 | O9743: Furniture | P9743: Bookcases | Q9743: Riverside Palais Royal Lawyers Bookcase, Royale Cherry Finish | R9743: 4404.9 | S9743: =SUM(R9743:R19542) -> 16604.098 | T9743: =COUNT(R9743:R19542) -> 59 | U9743: =IF(R9743>=500,"High","Low") -> High
A9744: 9743 | B9744: CA-2018-131303 | C9744: 43432 | D9744: 43436 | E9744: Standard Class | F9744: EP-13915 | G9744: Emily Phan | H9744: Consumer | I9744: United States | J9744: San Diego | K9744: California | L9744: 92037 | M9744: West | N9744: OFF-LA-10001074 | O9744: Office Supplies | P9744: Labels | Q9744: Round Specialty Laser Printer Labels | R9744: 62.65 | S9744: =SUM(R9744:R19543) -> 12199.198 | T9744: =COUNT(R9744:R19543) -> 58 | U9744: =IF(R9744>=500,"High","Low") -> Low
A9745: 9744 | B9745: CA-2017-137127 | C9745: 42902 | D9745: 42908 | E9745: Standard Class | F9745: JJ-15445 | G9745: Jennifer Jackson | H9745: Consumer | I9745: United States | J9745: Newark | K9745: Delaware | L9745: 19711 | M9745: East | N9745: OFF-LA-10001641 | O9745: Office Supplies | P9745: Labels | Q9745: Avery 518 | R9745: 9.45 | S9745: =SUM(R9745:R19544) -> 12136.548 | T9745: =COUNT(R9745:R19544) -> 57 | U9745: =IF(R9745>=500,"High","Low") -> Low
A9746: 9745 | B9746: CA-2018-141782 | C9746: 43121 | D9746: 43125 | E9746: Standard Class | F9746: BE-11410 | G9746: Bobby Elias | H9746: Consumer | I9746: United States | J9746: Aurora | K9746: Illinois | L9746: 60505 | M9746: Central | N9746: OFF-EN-10002230 | O9746: Office Supplies | P9746: Envelopes | Q9746: Airmail Envelopes | R9746: 268.576 | S9746: =SUM(R9746:R19545) -> 12127.098 | T9746: =COUNT(R9746:R19545) -> 56 | U9746: =IF(R9746>=500,"High","Low") -> Low
A9747: 9746 | B9747: CA-2018-137505 | C9747: 43428 | D9747: 43428 | E9747: Same Day | F9747: BP-11290 | G9747: Beth Paige | H9747: Consumer | I9747: United States | J9747: Los Angeles | K9747: California | L9747: 90008 | M9747: West | N9747: FUR-TA-10000617 | O9747: Furniture | P9747: Tables | Q9747: Hon Practical Foundations 30 x 60 Training Table, Light Gray/Charcoal | R9747: 364.08 | S9747: =SUM(R9747:R19546) -> 11858.522 | T9747: =COUNT(R9747:R19546) -> 55 | U9747: =IF(R9747>=500,"High","Low") -> Low
A9748: 9747 | B9748: CA-2018-137505 | C9748: 43428 | D9748: 43428 | E9748: Same Day | F9748: BP-11290 | G9748: Beth Paige | H9748: Consumer | I9748: United States | J9748: Los Angeles | K9748: California | L9748: 90008 | M9748: West | N9748: FUR-TA-10001676 | O9748: Furniture | P9748: Tables | Q9748: Hon 61000 Series Interactive Training Tables | R9748: 71.088 | S9748: =SUM(R9748:R19547) -> 11494.442 | T9748: =COUNT(R9748:R19547) -> 54 | U9748: =IF(R9748>=500,"High","Low") -> Low
A9749: 9748 | B9749: US-2015-140914 | C9749: 42319 | D9749: 42323 | E9749: Standard Class | F9749: BH-11710 | G9749: Brosina Hoffman | H9749: Consumer | I9749: United States | J9749: Chicago | K9749: Illinois | L9749: 60653 | M9749: Central | N9749: FUR-FU-10000175 | O9749: Furniture | P9749: Furnishings | Q9749: DAX Wood Document Frame. | R9749: 10.984 | S9749: =SUM(R9749:R19548) -> 11423.354 | T9749: =COUNT(R9749:R19548) -> 53 | U9749: =IF(R9749>=500,"High","Low") -> Low
A9750: 9749 | B9750: US-2015-140914 | C9750: 42319 | D9750: 42323 | E9750: Standard Class | F9750: BH-11710 | G9750: Brosina Hoffman | H9750: Consumer | I9750: United States | J9750: Chicago | K9750: Illinois | L9750: 60653 | M9750: Central | N9750: FUR-CH-10003379 | O9750: Furniture | P9750: Chairs | Q9750: Global Commerce Series High-Back Swivel/Tilt Chairs | R9750: 797.944 | S9750: =SUM(R9750:R19549) -> 11412.37 | T9750: =COUNT(R9750:R19549) -> 52 | U9750: =IF(R9750>=500,"High","Low") -> High
A9751: 9750 | B9751: CA-2017-158358 | C9751: 42798 | D9751: 42802 | E9751: Standard Class | F9751: EM-13810 | G9751: Eleni McCrary | H9751: Corporate | I9751: United States | J9751: Dover | K9751: New Hampshire | L9751: 3820 | M9751: East | N9751: TEC-AC-10002567 | O9751: Technology | P9751: Accessories | Q9751: Logitech G602 Wireless Gaming Mouse | R9751: 159.98 | S9751: =SUM(R9751:R19550) -> 10614.426 | T9751: =COUNT(R9751:R19550) -> 51 | U9751: =IF(R9751>=500,"High","Low") -> Low
A9752: 9751 | B9752: CA-2017-113390 | C9752: 43019 | D9752: 43023 | E9752: Standard Class | F9752: EP-13915 | G9752: Emily Phan | H9752: Consumer | I9752: United States | J9752: Chicago | K9752: Illinois | L9752: 60610 | M9752: Central | N9752: OFF-AR-10003183 | O9752: Office Supplies | P9752: Art | Q9752: Avery Fluorescent Highlighter Four-Color Set | R9752: 5.344 | S9752: =SUM(R9752:R19551) -> 10454.446 | T9752: =COUNT(R9752:R19551) -> 50 | U9752: =IF(R9752>=500,"High","Low") -> Low
A9753: 9752 | B9753: CA-2017-113390 | C9753: 43019 | D9753: 43023 | E9753: Standard Class | F9753: EP-13915 | G9753: Emily Phan | H9753: Consumer | I9753: United States | J9753: Chicago | K9753: Illinois | L9753: 60610 | M9753: Central | N9753: OFF-AR-10001446 | O9753: Office Supplies | P9753: Art | Q9753: Newell 309 | R9753: 27.72 | S9753: =SUM(R9753:R19552) -> 10449.102 | T9753: =COUNT(R9753:R19552) -> 49 | U9753: =IF(R9753>=500,"High","Low") -> Low
...

Sheet KPI Analysis
A1: KPI Name | B1: Values
A2: Total Sales | B2: =SUM(train!R2:R9801) -> 2261536.8
A3: Total Orders | B3: =COUNTA(_xlfn.UNIQUE(train!B2:B9801)) -> 4922
A4: Total Customers | B4: =COUNTA(_xlfn.UNIQUE(train!F2:F9801)) -> 793
A5: Total Products | B5: =COUNTA(_xlfn.UNIQUE(train!N2:N9801)) -> 1861
A6: Average Order Value | B6: =B2/B3 -> 459.47517
A7: West Region Sales | B7: =SUMIFS(train!R2:R9801,train!M2:M9801,"West") -> 710219.68
A8: Technology Sales | B8: =SUMIFS(train!R2:R9801,train!O2:O9801,"Technology") -> 827455.87
